flask_rest_paginate/__init__.py
flask_rest_paginate-1.1.1.dist-info/LICENSE.txt
flask_rest_paginate-1.1.1.dist-info/METADATA
flask_rest_paginate-1.1.1.dist-info/WHEEL
flask_rest_paginate-1.1.1.dist-info/top_level.txt
flask_rest_paginate-1.1.1.dist-info/RECORD
