Metadata-Version: 2.1
Name: flask-rest-paginate
Version: 1.1.1
Summary: Pagination extension for flask-restful
Home-page: https://github.com/mtShaikh/flask-rest-paginate
Author: mtShaikh
Author-email: shaikh.taha95@gmail.com
License: MIT
Keywords: rest flask-restful pagination flask
Platform: UNKNOWN
Classifier: Development Status :: 3 - Alpha
Classifier: Framework :: Flask
Classifier: Intended Audience :: Developers
Classifier: License :: OSI Approved :: MIT License
Classifier: Programming Language :: Python :: 3
Requires-Dist: flask-sqlalchemy
Requires-Dist: flask-restful
